nsface_match_cpu/__init__.py
nsface_match_cpu/face/__init__.py
nsface_match_cpu/face/common.py
nsface_match_cpu/face/__pycache__/__init__.cpython-38.pyc
nsface_match_cpu/face/__pycache__/common.cpython-38.pyc
nsface_match_cpu/model/__init__.py
nsface_match_cpu/model/load_arcface.py
nsface_match_cpu/model/load_onnx.py
nsface_match_cpu/model/load_vino.py
nsface_match_cpu/model/__pycache__/__init__.cpython-38.pyc
nsface_match_cpu/model/__pycache__/load_arcface.cpython-38.pyc
nsface_match_cpu/model/__pycache__/load_onnx.cpython-38.pyc
nsface_match_cpu/model/__pycache__/load_vino.cpython-38.pyc
nsface_match_cpu_python-0.0.14.dist-info/METADATA
nsface_match_cpu_python-0.0.14.dist-info/WHEEL
nsface_match_cpu_python-0.0.14.dist-info/top_level.txt
nsface_match_cpu_python-0.0.14.dist-info/RECORD
