Metadata-Version: 2.1
Name: nsface-match-cpu-python
Version: 0.0.14
Summary: nsense_face package CPU version
Home-page: UNKNOWN
Author: minsuny
Author-email: minsun.y@nsensecorp.com
License: UNKNOWN
Platform: UNKNOWN
Requires-Python: >=3
Requires-Dist: numpy
Requires-Dist: onnxruntime
Requires-Dist: openvino (==2022.2.0)
